<operation>
  <QUERYDESC NAMESPACE="SIRIUS" ENTITY="FuBOMDataLists" DATASETFORMAT="XML" MAXROWS="0">
    <RESULTFIELDS>
      <METAITEM TAG="Description">Description</METAITEM>
    </RESULTFIELDS>
    <CRITERIA>
      <METAITEM NAME="ListName" OPERATOR="=">
        <VALUE>#ListName#</VALUE>
      </METAITEM>
      <METAITEM NAME="Code" OPERATOR="=">
        <VALUE>#Code#</VALUE>
      </METAITEM>
      <METAITEM NAME="Expired" OPERATOR="=">
        <VALUE>0</VALUE>
      </METAITEM>
    </CRITERIA>
  </QUERYDESC>
</operation>